gooey/__init__.py
gooey/__main__.py
gooey/examples/__init__.py
gooey/examples/aaaaaa.py
gooey/examples/aaab.py
gooey/examples/advanced_group_usage.py
gooey/examples/all_widgets.py
gooey/examples/argopt_example.py
gooey/examples/asdfgsd.py
gooey/examples/asdfwaerwer.py
gooey/examples/asdfwef.py
gooey/examples/atemp.py
gooey/examples/cols.py
gooey/examples/dynamic_updates.py
gooey/examples/eee.py
gooey/examples/error_demo.py
gooey/examples/example_progress_bar_1.py
gooey/examples/foo.py
gooey/examples/foo2.py
gooey/examples/force_start_demo.py
gooey/examples/grtgtrherth.py
gooey/examples/issue100.py
gooey/examples/issue101.py
gooey/examples/issue147.py
gooey/examples/issue199.py
gooey/examples/issue26.py
gooey/examples/issue280.py
gooey/examples/issue309.py
gooey/examples/issue349.py
gooey/examples/issue351.py
gooey/examples/issue355.py
gooey/examples/issue3555.py
gooey/examples/issue356.py
gooey/examples/issue368.py
gooey/examples/issue377.py
gooey/examples/issue381.py
gooey/examples/issue385.py
gooey/examples/issue395.py
gooey/examples/issue397.py
gooey/examples/issue399.py
gooey/examples/issue400.py
gooey/examples/issue404.py
gooey/examples/issue405.py
gooey/examples/issue408.py
gooey/examples/issue438.py
gooey/examples/issue448.py
gooey/examples/issue462.py
gooey/examples/issue463.py
gooey/examples/issue469.py
gooey/examples/issue470.py
gooey/examples/issue495.py
gooey/examples/issue496.py
gooey/examples/issue497.py
gooey/examples/issue500.py
gooey/examples/issue505.py
gooey/examples/issue511.py
gooey/examples/issue517.py
gooey/examples/issue518.py
gooey/examples/issue526.py
gooey/examples/issue527.py
gooey/examples/issue535.py
gooey/examples/issue547.py
gooey/examples/issue559.py
gooey/examples/issue561.py
gooey/examples/issue571.py
gooey/examples/issue590.py
gooey/examples/issue591.py
gooey/examples/issue592.py
gooey/examples/issue594.py
gooey/examples/issue594a.py
gooey/examples/issue594b.py
gooey/examples/issue604.py
gooey/examples/issue609.py
Gooey-1.0.8.1.dist-info/LICENSE.txt
Gooey-1.0.8.1.dist-info/METADATA
Gooey-1.0.8.1.dist-info/WHEEL
Gooey-1.0.8.1.dist-info/dependency_links.txt
Gooey-1.0.8.1.dist-info/top_level.txt
Gooey-1.0.8.1.dist-info/RECORD
