Metadata-Version: 1.1
Name: Gooey
Version: 1.0.8.1
Summary: Turn (almost) any command line program into a full GUI application with one line
Home-page: http://pypi.python.org/pypi/Gooey/
Author: Chris Kiehl
Author-email: audionautic@gmail.com
License: MIT
Platform: UNKNOWN
Classifier: Development Status :: 4 - Beta
Classifier: Intended Audience :: Developers
Classifier: Topic :: Desktop Environment
Classifier: Topic :: Software Development :: Build Tools
Classifier: Topic :: Software Development :: Widget Sets
Classifier: Programming Language :: Python :: 2.7
Classifier: Programming Language :: Python :: 3
Classifier: License :: OSI Approved :: MIT License
